MANIFEST.in
README.rst
setup.py
pyclits/__init__.py
pyclits/data_loaders.py
pyclits/empirical_model.py
pyclits/functions.py
pyclits/geofield.py
pyclits/mutual_inf.py
pyclits/ssa.py
pyclits/surrogates.py
pyclits/var_model.py
pyclits/var_model_acc.pyx
pyclits/var_model_acc.pyxbld
pyclits/wavelet_analysis.py
pyclits.egg-info/PKG-INFO
pyclits.egg-info/SOURCES.txt
pyclits.egg-info/dependency_links.txt
pyclits.egg-info/not-zip-safe
pyclits.egg-info/requires.txt
pyclits.egg-info/top_level.txt