Metadata-Version: 1.1
Name: pyclits
Version: 0.1
Summary: Python Climate Time Series package
Home-page: https://github.com/jajcayn/pyclits
Author: Nikola Jajcay
Author-email: jajcay@cs.cas.cz
License: MIT
Keywords: time series analysis climate data
Platform: UNKNOWN
Classifier: Development Status :: 4 - Beta
Classifier: Intended Audience :: Science/Research
Classifier: Programming Language :: Python :: 2.7
Classifier: Topic :: Scientific/Engineering :: Atmospheric Science
Classifier: License :: OSI Approved :: MIT License
